dat_terminal/__init__.py
dat_terminal/colors.py
dat_terminal/config.py
dat_terminal/dat_terminal.py
dat_terminal/input_handler.py
dat_terminal/paths.py
dat_terminal/themes.py
dat_terminal/commands/__init__.py
dat_terminal/commands/command.py
dat_terminal/commands/invoker.py
dat_terminal/logger/__init__.py
dat_terminal/logger/color_formatter.py
dat_terminal/utils/__init__.py
dat_terminal/utils/string_utils.py
dat_terminal-0.0.1b0.dist-info/LICENSE
dat_terminal-0.0.1b0.dist-info/METADATA
dat_terminal-0.0.1b0.dist-info/WHEEL
dat_terminal-0.0.1b0.dist-info/top_level.txt
dat_terminal-0.0.1b0.dist-info/RECORD
