Metadata-Version: 2.1
Name: dat-terminal
Version: 0.0.1b0
Summary: An interactive terminal for applications that needs custom commands.
Home-page: https://github.com/DatDarkAlpaca/dat-terminal
Author: DatAlpaca
License: MIT
Platform: UNKNOWN
Classifier: Development Status :: 1 - Planning
Classifier: License :: OSI Approved :: MIT License
Classifier: Intended Audience :: Developers
Classifier: Natural Language :: English
Classifier: Operating System :: OS Independent
Classifier: Programming Language :: Python :: 3.8
Classifier: Topic :: Software Development :: Libraries
Classifier: Topic :: Software Development :: Libraries :: Python Modules
Classifier: Topic :: Utilities
Classifier: Typing :: Typed
Requires-Python: >=3.8.0
License-File: LICENSE
Requires-Dist: PyYAML
Requires-Dist: colorama
Requires-Dist: termcolor
